{
  "prescription": {
    "rt_ct_pres": {
      "path": "/{clinical_trial}/{test_centre}/Patient Plans/Patient {centre_patient_no}/CT/",
      "display_name": "RT CT (prescription level)",
      "field_type": "folder",
      "level": "prescription",
      "allowed": [
        "application/dicom"
      ]
    },
    "rt_dose_pres": {
      "path": "/{clinical_trial}/{test_centre}/Patient Plans/Patient {centre_patient_no}/Dose/",
      "display_name": "RT Dose (prescription level)",
      "field_type": "file",
      "level": "prescription",
      "allowed": [
        "application/dicom"
      ],
      "file_name": []
    },
    "rt_mri_pres": {
      "path": "/{clinical_trial}/{test_centre}/Patient Plans/Patient {centre_patient_no}/MRI/",
      "display_name": "RT MRI",
      "field_type": "folder",
      "level": "prescription",
      "allowed": [
        "application/dicom"
      ]
    },
    "rt_plan_pres": {
      "path": "/{clinical_trial}/{test_centre}/Patient Plans/Patient {centre_patient_no}/Plan/",
      "display_name": "RT Plan (prescription level)",
      "field_type": "file",
      "level": "prescription",
      "allowed": [
        "application/dicom"
      ],
      "file_name": []
    },
    "rt_structure_pres": {
      "path": "/{clinical_trial}/{test_centre}/Patient Structure Sets/Patient {centre_patient_no}/{fraction_name}/",
      "display_name": "RT Structure (prescription level)",
      "field_type": "folder",
      "level": "fraction",
      "allowed": [
        "application/dicom"
      ]
    },
    "planned_dvh_pres": {
      "path": "/{clinical_trial}/{test_centre}/Dose Reconstruction/DVH/Patient {centre_patient_no}/",
      "display_name": "Planned DVH (prescription level)",
      "field_type": "file",
      "level": "prescription",
      "allowed": [
        "text/plain",
        "text/csv"
      ]
    },
    "planned_dicom_pres": {
      "path": "/{clinical_trial}/{test_centre}/Dose Reconstruction/DICOM/Patient {centre_patient_no}/",
      "display_name": "Planned DICOM (prescription level)",
      "field_type": "file",
      "level": "prescription",
      "allowed": ["application/dicom"]
    },
    "centroid_pres": {
      "path": "/{clinical_trial}/{test_centre}/Patient Files/Patient {centre_patient_no}/",
      "display_name": "Centroid (prescription level)",
      "field_type": "file",
      "level": "prescription",
      "allowed": [
        "text/plain"
      ],
      "file_name": []
    }
  },
  "fraction": {
    "rt_ct_fraction": {
      "path": "/{clinical_trial}/{test_centre}/Patient Plans/Patient {centre_patient_no}/CT/",
      "display_name": "RT CT (fraction level)",
      "field_type": "folder",
      "level": "fraction",
      "allowed": [
        "application/dicom"
      ]
    },
    "rt_dose_fraction": {
      "path": "/{clinical_trial}/{test_centre}/Patient Plans/Patient {centre_patient_no}/Dose/",
      "display_name": "RT Dose (fraction level)",
      "field_type": "file",
      "level": "fraction",
      "allowed": [
        "application/dicom"
      ],
      "file_name": []
    },
    "rt_plan_fraction": {
      "path": "",
      "display_name": "",
      "field_type": "file",
      "level": "",
      "allowed": []
    },
    "rt_structure_fraction": {
      "path": "",
      "display_name": "",
      "field_type": "file",
      "level": "",
      "allowed": []
    },
    "centroid_fraction": {
      "path": "/{clinical_trial}/{test_centre}/Patient Files/Patient {centre_patient_no}/",
      "display_name": "Centroid (fraction level)",
      "field_type": "file",
      "level": "fraction",
      "allowed": [
        "text/plain",
        "text/csv",
        "text/xlsx"
      ],
      "file_name": [
        "Centroid"
      ]
    },
    "KIM threshold": {
      "path": "/{clinical_trial}/{test_centre}/Patient Files/Patient {centre_patient_no}/",
      "display_name": "KIM threshold (fraction level)",
      "field_type": "file",
      "level": "fraction",
      "allowed": ["text/plain"]
    },
    "kim_logs_path": {
      "path": "/{clinical_trial}/{test_centre}/Patient Measured Motion/Patient {centre_patient_no}/",
      "display_name": "KIM Logs",
      "field_type": "folder",
      "level": "fraction",
      "allowed": [
        "text/plain",
        "text/csv"
      ]
    },
    "kv_images_path": {
      "path": "/{clinical_trial}/{test_centre}/Patient Images/Patient {centre_patient_no}/",
      "display_name": "KV Images",
      "field_type": "folder",
      "level": "fraction",
      "allowed": [
        "image/tiff",
        "image/hnd",
        "image/hnc",
        "image/his",
        "image/jpg",
        "image/png",
        "image/dicom",
        "application/dicom",
        "application/octet-stream",
        "text/plain",
        "text/xml"
        "text/csv",
      ]
    },
    "mv_images_path": {
      "path": "/{clinical_trial}/{test_centre}/Patient Images/Patient {centre_patient_no}/",
      "display_name": "MV Images",
      "field_type": "folder",
      "level": "fraction",
      "allowed": [
        "image/tiff",
        "image/hnd",
        "image/hnc",
        "image/his",
        "image/jpg",
        "image/png",
        "image/dicom",
        "application/dicom",
        "application/octet-stream",
        "text/plain",
        "text/xml"
        "text/csv",
      ]
    },
    "metrics_path": {
      "path": "/{clinical_trial}/{test_centre}/Triangulation/Patient {centre_patient_no}/",
      "display_name": "Metrics",
      "field_type": "file",
      "level": "fraction",
      "allowed": [
        "text/plain",
        "application/vnd.ms-excel",
        "application/vnd.openxmlformats-officedocument.spreadsheetml.sheet",
        "application/vnd.oasis.opendocument.spreadsheet",
        "text/csv"
      ]
    },
    "triangulation_path": {
      "path": "/{clinical_trial}/{test_centre}/Triangulation/Patient {centre_patient_no}/",
      "display_name": "Triangulation Files",
      "field_type": "file",
      "level": "fraction",
      "allowed": [
        "text/plain",
        "application/vnd.ms-excel",
        "application/vnd.openxmlformats-officedocument.spreadsheetml.sheet",
        "application/vnd.oasis.opendocument.spreadsheet",
        "text/csv"
      ]
    },
    "trajectory_logs_path": {
      "path": "/{clinical_trial}/{test_centre}/Trajectory Logs/Patient {centre_patient_no}/",
      "display_name": "Trajectory Logs Files",
      "field_type": "folder",
      "level": "fraction",
      "allowed": [
        "application/octet-stream",
        "application/zip",
        "application/x-7z-compressed",
        "application/gzip",
        "application/x-bzip2",
        "application/x-bzip"
      ]
    },
    "dvh_track_path": {
      "path": "/{clinical_trial}/{test_centre}/Dose Reconstruction/DVH/Patient {centre_patient_no}/",
      "display_name": "DVH Track",
      "field_type": "file",
      "level": "fraction",
      "allowed": [
        "text/plain",
        "text/csv"
      ]
    },
    "dvh_no_track_path": {
      "path": "/{clinical_trial}/{test_centre}/Dose Reconstruction/DVH/Patient {centre_patient_no}/",
      "display_name": "DVH No Track",
      "field_type": "file",
      "level": "fraction",
      "allowed": [
        "text/plain",
        "text/csv"
      ]
    },
    "planned_dvh_fraction": {
      "path": "/{clinical_trial}/{test_centre}/Dose Reconstruction/DVH/Patient {centre_patient_no}/",
      "display_name": "Planned DVH (fraction level)",
      "field_type": "file",
      "level": "prescription",
      "allowed": [
        "text/plain",
        "text/csv"
      ]
    },
    "planned_dicom_fraction": {
      "path": "/{clinical_trial}/{test_centre}/Dose Reconstruction/DICOM/Patient {centre_patient_no}/",
      "display_name": "Planned DICOM (fraction level)",
      "field_type": "file",
      "level": "fraction",
      "allowed": ["application/dicom"]
    },
    "dicom_track_plan_path": {
      "path": "/{clinical_trial}/{test_centre}/Dose Reconstruction/DICOM/Patient {centre_patient_no}/",
      "display_name": "DICOM Track Plan",
      "field_type": "file",
      "level": "fraction",
      "allowed": [
        "application/dicom"
      ]
    },
     "RPM_path": {
      "path": "/{clinical_trial}/{test_centre}/RPM/Patient {centre_patient_no}/",
      "display_name": "RPM",
      "field_type": "folder",
      "level": "fraction",
      "allowed": [
        "application/plain text"
      ]
    },
    "dicom_no_track_plan_path": {
      "path": "/{clinical_trial}/{test_centre}/Dose Reconstruction/DICOM/Patient {centre_patient_no}/",
      "display_name": "DICOM No Track Plan",
      "field_type": "file",
      "level": "fraction",
      "allowed": [
        "application/dicom"
      ]
    }
  }
}
